level_ws_client/__init__.py
level_ws_client/client.py
level_ws_client/protocol.py
level_ws_client/py.typed
level_ws_client/ws.py
level_ws_client-0.1.0.dist-info/METADATA
level_ws_client-0.1.0.dist-info/WHEEL
level_ws_client-0.1.0.dist-info/licenses/LICENSE
level_ws_client-0.1.0.dist-info/RECORD
