Metadata-Version: 2.4
Name: level-ws-client
Version: 0.1.0
Summary: Async WebSocket and HTTP client for Level Lock API
Project-URL: Homepage, https://github.com/LevelHome/level-ws-client
Project-URL: Repository, https://github.com/LevelHome/level-ws-client
Author: Level Lock
License: MIT License
License-File: LICENSE
Keywords: iot,level-lock,smart-home,websocket
Classifier: Development Status :: 4 - Beta
Classifier: Intended Audience :: Developers
Classifier: License :: OSI Approved :: MIT License
Classifier: Programming Language :: Python :: 3
Classifier: Programming Language :: Python :: 3.10
Classifier: Programming Language :: Python :: 3.11
Classifier: Programming Language :: Python :: 3.12
Classifier: Programming Language :: Python :: 3.13
Classifier: Topic :: Home Automation
Classifier: Typing :: Typed
Requires-Python: >=3.10
Requires-Dist: aiohttp>=3.8.0
Provides-Extra: dev
Requires-Dist: black>=24.0.0; extra == 'dev'
Requires-Dist: build>=1.0.0; extra == 'dev'
Requires-Dist: ruff>=0.5.0; extra == 'dev'
